[
    {
        "title": "Jojo Rabbit",
        "date": "2022-01-28"
    },
    {
        "title": "Parasite",
        "date": "2022-02-04",
        "year": 2019
    },
    {
        "title": "Green Book",
        "date": "2022-03-04"
    },
    {
        "title": "The Revenant",
        "date": "2022-03-11"
    },
    {
        "title": "Movie 43",
        "date": "2022-03-18"
    },
    {
        "title": "Donnie Darko",
        "date": "2022-03-25"
    },
    {
        "title": "The Rock: Fels der Entscheidung",
        "date": "2022-04-01"
    },
    {
        "title": "Akira",
        "date": "2022-04-08",
        "year": 1991
    },
    {
        "title": "American Psycho",
        "date": "2022-04-22"
    },
    {
        "title": "Shoplifters",
        "date": "2022-04-29",
        "year": 2018
    },
    {
        "title": "Arrival",
        "date": "2022-05-06"
    },
    {
        "title": "Gran Torino",
        "date": "2022-05-27"
    },
    {
        "title": "Praxis Dr Hasenbein",
        "date": "2022-06-03"
    },
    {
        "title": "Memento",
        "date": "2022-07-22"
    },
    {
        "title": "Victoria",
        "date": "2022-07-29",
        "year": 2015
    },
    {
        "title": "Isle of Dogs",
        "date": "2022-08-12"
    },
    {
        "title": "Once Upon a Time in Hollywood"
    },
    {
        "title": "The Death of Stalin"
    },
    {
        "title": "Waynes World"
    },
    {
        "title": "Lost in Translation",
        "date": "2022-09-16"
    },
    {
        "title": "St. Vincent"
    },
    {
        "title": "Kiss the Cook",
        "year": 2014
    },
    {
        "title": "Mac and Me",
        "date": "2022-10-28"
    },
    {
        "title": "Spaceballs",
        "date": "2022-11-04"
    },
    {
        "title": "Palm Springs"
    },
    {
        "title": "Edge of Tomorrow"
    },
    {
        "title": "Die Gefährten",
        "apiTitle": "Der Herr der Ringe: Die Gefährten"
    },
    {
        "title": "Die zwei Türme"
    },
    {
        "title": "Die Rückkehr des Königs",
        "apiTitle": "Der Herr der Ringe: Die Rückkehr des Königs"},
    {
        "title": "Watchmen"
    },
    {
        "title": "Die Ritter der Kokosnuss",
        "date": "2022-12-30"
    }
]
